fidax/__init__.py
fidax/fid.py
fidax/inception.py
fidax/py.typed
fidax/test_fid_metric.py
fidax-0.3.1.dist-info/METADATA
fidax-0.3.1.dist-info/WHEEL
fidax-0.3.1.dist-info/licenses/LICENSE
fidax-0.3.1.dist-info/licenses/NOTICE
fidax-0.3.1.dist-info/RECORD
