Metadata-Version: 2.4
Name: fidax
Version: 0.3.1
Summary: An sklearn-style FID metric class for Jax
Project-URL: Homepage, https://github.com/wittenator/fidax
Project-URL: Issues, https://github.com/wittenator/fidax/issues
Author-email: wittenator <9154515+wittenator@users.noreply.github.com>
License-File: LICENSE
License-File: NOTICE
Requires-Python: >=3.10
Requires-Dist: flax>=0.10.6
Requires-Dist: jax[cuda12]>=0.5.3
Requires-Dist: jaxlib>=0.5.3
Requires-Dist: jaxtyping>=0.3.3
Requires-Dist: requests>=2.32.4
